dt_shell/__init__.py
dt_shell/constants.py
dt_shell/environments.py
dt_shell/exceptions.py
dt_shell/hub.py
dt_shell/logging.py
dt_shell/profile.py
dt_shell/shell.py
dt_shell/statistics.py
dt_shell/tasks.py
dt_shell/typing.py
dt_shell/utils.py
dt_shell/assets/dts-completion.bash
dt_shell/assets/get-pip.py
dt_shell/assets/requirements.txt
dt_shell/checks/__init__.py
dt_shell/checks/environment.py
dt_shell/checks/packages.py
dt_shell/checks/version.py
dt_shell/commands/__init__.py
dt_shell/commands/autocomplete.py
dt_shell/commands/commands.py
dt_shell/commands/importer.py
dt_shell/commands/repository.py
dt_shell/compatibility/__init__.py
dt_shell/compatibility/commands_.py
dt_shell/compatibility/config.py
dt_shell/compatibility/duckietown_tokens.py
dt_shell/compatibility/env_checks.py
dt_shell/compatibility/tokens_cli.py
dt_shell/compatibility/version_check.py
dt_shell/compatibility/migrations/__init__.py
dt_shell/compatibility/migrations/migrations.py
dt_shell/database/__init__.py
dt_shell/database/database.py
dt_shell/database/utils.py
dt_shell/embedded/command_descriptions.yaml
dt_shell/embedded/__command_set__/configuration.py
dt_shell/embedded/__command_set__/init.py
dt_shell/embedded/__command_set__/requirements.txt
dt_shell/embedded/commands/__init__.py
dt_shell/embedded/commands/command.py
dt_shell/embedded/exit/__init__.py
dt_shell/embedded/exit/command.py
dt_shell/embedded/exit/configuration.py
dt_shell/embedded/install/__init__.py
dt_shell/embedded/install/command.py
dt_shell/embedded/install/configuration.py
dt_shell/embedded/profile/__init__.py
dt_shell/embedded/profile/dependencies/__init__.py
dt_shell/embedded/profile/dependencies/reinstall/__init__.py
dt_shell/embedded/profile/dependencies/reinstall/command.py
dt_shell/embedded/profile/dependencies/reinstall/configuration.py
dt_shell/embedded/profile/list/__init__.py
dt_shell/embedded/profile/list/command.py
dt_shell/embedded/profile/list/configuration.py
dt_shell/embedded/profile/new/__init__.py
duckietown_shell-6.2.18.dist-info/licenses/LICENSE.pdf
duckietown_shell-6.2.18.dist-info/METADATA
duckietown_shell-6.2.18.dist-info/WHEEL
duckietown_shell-6.2.18.dist-info/entry_points.txt
duckietown_shell-6.2.18.dist-info/top_level.txt
duckietown_shell-6.2.18.dist-info/RECORD
