Metadata-Version: 2.4
Name: duckietown-shell
Version: 6.2.18
Download-URL: http://github.com/duckietown/duckietown-shell/tarball/6.2.18
License-File: LICENSE.pdf
Requires-Dist: termcolor<3,>=2.3.0
Requires-Dist: requests<3,>=2.31.0
Requires-Dist: pyyaml!=5.4.0,!=5.4.1,!=6.0.0,<7
Requires-Dist: pyfiglet<1,>=0.8.0
Requires-Dist: questionary<3,>=2.0.1
Requires-Dist: argcomplete<4,>=3.1.4
Requires-Dist: coloredlogs<16,>=15.0
Requires-Dist: filelock<4,>=3
Requires-Dist: dockertown<1,>=0.2.5
Requires-Dist: dtproject<2,>=1.0.12
Requires-Dist: dt-authentication<3,>=2.1.4
Requires-Dist: dt-data-api<3,>=2.0.0
Requires-Dist: setuptools<67.3.0
Requires-Dist: docker<7,>=6.1.3
Dynamic: download-url
Dynamic: license-file
Dynamic: requires-dist
